setup.py
lazyobject/__init__.py
lazyobject.egg-info/PKG-INFO
lazyobject.egg-info/SOURCES.txt
lazyobject.egg-info/dependency_links.txt
lazyobject.egg-info/top_level.txt