Metadata-Version: 1.0
Name: lazyobject
Version: 0.0.1
Summary: A thread-safe LazyObject class.
Home-page: https://github.com/apn-online/lazyobject
Author: Raymond Butcher
Author-email: randomy@gmail.com
License: MIT
Platform: UNKNOWN
